pylantir/__init__.py
pylantir/db_setup.py
pylantir/models.py
pylantir/mwl_server.py
pylantir/populate_db.py
pylantir/redcap_to_db.py
pylantir/cli/__init__.py
pylantir/cli/run.py
pylantir/config/mwl_config.json
pylantir-0.1.3.dist-info/entry_points.txt
pylantir-0.1.3.dist-info/licenses/LICENSE
pylantir-0.1.3.dist-info/WHEEL
pylantir-0.1.3.dist-info/METADATA
pylantir-0.1.3.dist-info/RECORD
